README.md
setup.py
Flask_Yolo2API.egg-info/PKG-INFO
Flask_Yolo2API.egg-info/SOURCES.txt
Flask_Yolo2API.egg-info/dependency_links.txt
Flask_Yolo2API.egg-info/requires.txt
Flask_Yolo2API.egg-info/top_level.txt
flask_yoloapi/__init__.py
flask_yoloapi/endpoint.py
flask_yoloapi/exceptions.py
flask_yoloapi/types.py
flask_yoloapi/utils.py
tests/__init__.py
tests/conftest.py
tests/mock_app.py
tests/test_app.py