Metadata-Version: 2.1
Name: Flask-Yolo2API
Version: 0.2.1
Summary: Simply the best Flask API library
Home-page: https://github.com/skftn/flask-yoloapi
Author: Sander Ferdinand, Daniel Ternyak
Author-email: sa.ferdinand@gmail.com
License: UNKNOWN
Keywords: flask api flapi yoloapi
Platform: UNKNOWN
Classifier: Development Status :: 4 - Beta
Classifier: Environment :: Web Environment
Classifier: Intended Audience :: Developers
Classifier: License :: OSI Approved :: MIT License
Classifier: Operating System :: OS Independent
Classifier: Topic :: Software Development :: Libraries :: Python Modules
Classifier: Topic :: Utilities
Classifier: Programming Language :: Python
